rtf/__init__.py
rtf/generate.py
rtf/server.py
rtf/service.py
rtf/generators/__init__.py
rtf/generators/base.py
rtf/generators/go.py
rtf/proto/__init__.py
rtf/proto/rtf_pb2.py
rtf/proto/rtf_pb2_grpc.py
rtf-0.0.1.dist-info/LICENSE
rtf-0.0.1.dist-info/METADATA
rtf-0.0.1.dist-info/WHEEL
rtf-0.0.1.dist-info/top_level.txt
rtf-0.0.1.dist-info/RECORD
